reactIDR/AUC.py
reactIDR/IDR_hmm.py
reactIDR/__init__.py
reactIDR/evaluate_IDR_csv.py
reactIDR/forward_backward.py
reactIDR/idr_wrapper_hmm.py
reactIDR/main.py
reactIDR/param_fit_hmm.py
reactIDR/plot_bargraph.py
reactIDR/prob_optimize.py
reactIDR/pvalue.py
reactIDR/reactivity_IDR.py
reactIDR/score_converter.py
reactIDR/utility.py
reactIDR/zero_inflated_p.py
reactIDR/cython/__init__.py
reactIDR/cython/fast_param_fit.cpython-39-darwin.so
reactIDR/cython/fast_param_fit.pyx
reactidr-2.0.3.dist-info/licenses/LICENSE
reactidr-2.0.3.dist-info/METADATA
reactidr-2.0.3.dist-info/WHEEL
reactidr-2.0.3.dist-info/entry_points.txt
reactidr-2.0.3.dist-info/top_level.txt
reactidr-2.0.3.dist-info/RECORD
