Metadata-Version: 2.4
Name: reactIDR
Version: 2.0.3
Summary: Implementation of the IDR (Irreproducible Discovery Rate) method for RNA reactivity data.
Author: carushi
Author-email: carushi <1845273+carushi@users.noreply.github.com>
License: GPL2
Project-URL: Homepage, https://github.com/carushi/reactIDR
Project-URL: Repository, https://github.com/carushi/reactIDR
Requires-Python: >=3.9
License-File: LICENSE
Requires-Dist: numpy>=2.0.2
Requires-Dist: scipy>=1.13.1
Requires-Dist: matplotlib
Requires-Dist: pandas>=2.2.3
Dynamic: author
Dynamic: license-file
Dynamic: requires-python
